telenium/__init__.py
telenium/client.py
telenium/execute.py
telenium/tests.py
telenium/web.py
telenium/xpath.py
telenium/mods/__init__.py
telenium/mods/telenium_client.py
telenium/static/index.html
telenium/static/css/app.css
telenium/static/css/bootstrap-theme.css
telenium/static/css/bootstrap-theme.css.map
telenium/static/css/bootstrap-theme.min.css
telenium/static/css/bootstrap.css
telenium/static/css/bootstrap.css.map
telenium/static/css/bootstrap.min.css
telenium/static/fonts/glyphicons-halflings-regular.eot
telenium/static/fonts/glyphicons-halflings-regular.svg
telenium/static/fonts/glyphicons-halflings-regular.ttf
telenium/static/fonts/glyphicons-halflings-regular.woff
telenium/static/fonts/glyphicons-halflings-regular.woff2
telenium/static/js/bootstrap.js
telenium/static/js/bootstrap.min.js
telenium/static/js/jquery-2.2.4.min.js
telenium/static/js/jquery-sortable.js
telenium/static/js/mustache.min.js
telenium/static/js/reconnecting-websocket.min.js
telenium/static/js/ui.js
telenium-0.5.1.dist-info/LICENSE
telenium-0.5.1.dist-info/METADATA
telenium-0.5.1.dist-info/WHEEL
telenium-0.5.1.dist-info/entry_points.txt
telenium-0.5.1.dist-info/top_level.txt
telenium-0.5.1.dist-info/RECORD
