Metadata-Version: 2.1
Name: telenium
Version: 0.5.1
Summary: Kivy automation, can be used to do GUI tests.
Home-page: http://github.com/tito/telenium
Author: Mathieu Virbel
Author-email: mat@meltingrocks.com
License: MIT License
Keywords: kivy,automate,unittest,wait,condition
Platform: any
Classifier: Development Status :: 4 - Beta
Classifier: Intended Audience :: Developers
Classifier: Intended Audience :: End Users/Desktop
Classifier: Intended Audience :: Information Technology
Classifier: Intended Audience :: Science/Research
Classifier: Intended Audience :: System Administrators
Classifier: License :: OSI Approved :: MIT License
Classifier: Operating System :: POSIX
Classifier: Operating System :: MacOS
Classifier: Operating System :: Unix
Classifier: Programming Language :: Python
Classifier: Programming Language :: Python :: 2
Classifier: Topic :: Software Development :: Libraries :: Python Modules
Classifier: Topic :: Software Development :: Build Tools
Classifier: Topic :: Internet
Classifier: Topic :: System :: Systems Administration
Classifier: Topic :: System :: Monitoring
License-File: LICENSE
Requires-Dist: Mako (>=1.0.6)
Requires-Dist: CherryPy (>=10.2.1)
Requires-Dist: ws4py (>=0.4.2)
Requires-Dist: json-rpc (>=1.10.3)
Requires-Dist: Werkzeug (>=0.12.2)
